LICENSE
MANIFEST.in
README.rst
requirements.txt
setup.py
gd.bot.egg-info/PKG-INFO
gd.bot.egg-info/SOURCES.txt
gd.bot.egg-info/dependency_links.txt
gd.bot.egg-info/entry_points.txt
gd.bot.egg-info/requires.txt
gd.bot.egg-info/top_level.txt
gd/bot/__init__.py
gd/bot/__main__.py
gd/bot/core.py
gd/bot/assets/auto.png
gd/bot/assets/auto_epic.png
gd/bot/assets/auto_featured.png
gd/bot/assets/comment_history.png
gd/bot/assets/copy.png
gd/bot/assets/creator_points.png
gd/bot/assets/cross.png
gd/bot/assets/demon.png
gd/bot/assets/demon_epic.png
gd/bot/assets/demon_featured.png
gd/bot/assets/diamond.png
gd/bot/assets/discord.png
gd/bot/assets/dislike.png
gd/bot/assets/download_song.png
gd/bot/assets/downloads.png
gd/bot/assets/easy.png
gd/bot/assets/easy_demon.png
gd/bot/assets/easy_demon_epic.png
gd/bot/assets/easy_demon_featured.png
gd/bot/assets/easy_epic.png
gd/bot/assets/easy_featured.png
gd/bot/assets/elder_mod.png
gd/bot/assets/extreme_demon.png
gd/bot/assets/extreme_demon_epic.png
gd/bot/assets/extreme_demon_featured.png
gd/bot/assets/failed.png
gd/bot/assets/friends.png
gd/bot/assets/hard.png
gd/bot/assets/hard_demon.png
gd/bot/assets/hard_demon_epic.png
gd/bot/assets/hard_demon_featured.png
gd/bot/assets/hard_epic.png
gd/bot/assets/hard_featured.png
gd/bot/assets/harder.png
gd/bot/assets/harder_epic.png
gd/bot/assets/harder_featured.png
gd/bot/assets/info.png
gd/bot/assets/insane.png
gd/bot/assets/insane_demon.png
gd/bot/assets/insane_demon_epic.png
gd/bot/assets/insane_demon_featured.png
gd/bot/assets/insane_epic.png
gd/bot/assets/insane_featured.png
gd/bot/assets/like.png
gd/bot/assets/medium_demon.png
gd/bot/assets/medium_demon_epic.png
gd/bot/assets/medium_demon_featured.png
gd/bot/assets/messages.png
gd/bot/assets/mod.png
gd/bot/assets/na.png
gd/bot/assets/na_epic.png
gd/bot/assets/na_featured.png
gd/bot/assets/next.png
gd/bot/assets/normal.png
gd/bot/assets/normal_epic.png
gd/bot/assets/normal_featured.png
gd/bot/assets/object_overflow.png
gd/bot/assets/play.png
gd/bot/assets/previous.png
gd/bot/assets/secret_coin.png
gd/bot/assets/star.png
gd/bot/assets/success.png
gd/bot/assets/twitch.png
gd/bot/assets/twitter.png
