Metadata-Version: 2.1
Name: gd.bot
Version: 0.1.1
Summary: Discord Bot which can interact with Geometry Dash servers, and much more!
Home-page: https://github.com/nekitdev/gd.bot
Author: nekitdev
Author-email: nekitdevofficial@gmail.com
License: MIT
Project-URL: Issue tracker, https://github.com/nekitdev/gd.bot/issues
Platform: UNKNOWN
Classifier: Development Status :: 2 - Pre-Alpha
Classifier: License :: OSI Approved :: MIT License
Classifier: Programming Language :: Python :: 3.6
Classifier: Programming Language :: Python :: 3.7
Classifier: Programming Language :: Python :: 3.8
Classifier: Natural Language :: English
Classifier: Operating System :: OS Independent
Requires-Python: >=3.6
